jarvis_orm/__init__.py
jarvis_orm/commands.py
jarvis_orm/engine.py
jarvis_orm/model.py
jarvis_orm/parse.py
jarvis_orm/utilities.py
jarvis_orm-0.0.10.dist-info/METADATA
jarvis_orm-0.0.10.dist-info/WHEEL
jarvis_orm-0.0.10.dist-info/licenses/LICENSE
jarvis_orm-0.0.10.dist-info/RECORD
