Metadata-Version: 2.3
Name: jarvis-orm
Version: 0.0.10
Summary: Python Object-Relational Mapping
Project-URL: Homepage, https://github.com/jarvisluke/jarvis-orm
Project-URL: Repository, https://github.com/jarvisluke/jarvis-orm.git
Project-URL: Bug Tracker, https://github.com/jarvisluke/jarvis-orm/issues
Project-URL: Changelog, https://github.com/me/jarvis-orm/blob/master/CHANGELOG.md
Author-email: Luke Jarvis <jarvislukeldj@gmail.com>
Maintainer-email: Luke Jarvis <jarvislukeldj@gmail.com>
License: MIT License
License-File: LICENSE
Keywords: orm,sql,sqlite,sqlite3
Classifier: Development Status :: 3 - Alpha
Classifier: License :: OSI Approved :: MIT License
Classifier: Operating System :: OS Independent
Classifier: Programming Language :: Python :: 3
Requires-Python: >=3.10
